ansible/module_utils/consul_acl.py
ansible/modules/consul_acl/__init__.py
ansible/modules/consul_acl/consul_acl_policy.py
ansible/modules/consul_acl/consul_acl_token.py
ansible_modules_consul_acl-0.4.0.dist-info/METADATA
ansible_modules_consul_acl-0.4.0.dist-info/RECORD
ansible_modules_consul_acl-0.4.0.dist-info/WHEEL
ansible_modules_consul_acl-0.4.0.dist-info/top_level.txt
