Metadata-Version: 2.1
Name: ansible-modules-consul-acl
Version: 0.4.0
Summary: Ansible modules for the Consul ACL system
Home-page: https://github.com/jsundh/ansible-modules-consul-acl
Author: Jakob Sundh
Author-email: jsundh@users.noreply.github.com
License: GNU GPL v3
Platform: UNKNOWN
Requires-Dist: ansible (>=2.4.0)
